turing_calculator_sagar
