Metadata-Version: 2.1
Name: turing-calculator-sagar
Version: 0.0.2
Summary: Simple Basic Calculator
Author: Sagar Yadav
Author-email: pipTuringCalculator@sagaryadav.com
License: UNKNOWN
Platform: UNKNOWN
